{
    "city": {
        "id": 4930956,
        "name": "Boston",
        "coord": {
            "lon": -71.0571,
            "lat": 42.3611
        },
        "country": "US",
        "population": 617594,
        "timezone": -14400
    },
    "cod": "200",
    "message": 16.9355088,
    "cnt": 17,
    "list": [
        {
            "dt": 1618502400,
            "sunrise": 1618480960,
            "sunset": 1618529116,
            "temp": {
                "day": 53.13,
                "min": 42.87,
                "max": 53.15,
                "night": 42.87,
                "eve": 44.92,
                "morn": 45.36
            },
            "feels_like": {
                "day": 50.22,
                "night": 42.94,
                "eve": 39.78,
                "morn": 42.94
            },
            "pressure": 1010,
            "humidity": 44,
            "weather": [
                {
                    "id": 501,
                    "main": "Rain",
                    "description": "moderate rain",
                    "icon": "10d"
                }
            ],
            "speed": 13.96,
            "deg": 94,
            "gust": 26.51,
            "clouds": 96,
            "pop": 1,
            "rain": 5.73
        },
        {
            "dt": 1618588800,
            "sunrise": 1618567264,
            "sunset": 1618615584,
            "temp": {
                "day": 46.8,
                "min": 39.87,
                "max": 46.8,
                "night": 41.47,
                "eve": 41.25,
                "morn": 40.26
            },
            "feels_like": {
                "day": 41.97,
                "night": 31.96,
                "eve": 38.3,
                "morn": 31.96
            },
            "pressure": 994,
            "humidity": 96,
            "weather": [
                {
                    "id": 501,
                    "main": "Rain",
                    "description": "moderate rain",
                    "icon": "10d"
                }
            ],
            "speed": 17.05,
            "deg": 71,
            "gust": 19.08,
            "clouds": 100,
            "pop": 1,
            "rain": 27.07
        },
        {
            "dt": 1618675200,
            "sunrise": 1618653569,
            "sunset": 1618702052,
            "temp": {
                "day": 41.23,
                "min": 36.72,
                "max": 42.71,
                "night": 40.59,
                "eve": 42.71,
                "morn": 36.72
            },
            "feels_like": {
                "day": 34.05,
                "night": 28.53,
                "eve": 38.3,
                "morn": 28.53
            },
            "pressure": 1006,
            "humidity": 81,
            "weather": [
                {
                    "id": 616,
                    "main": "Snow",
                    "description": "rain and snow",
                    "icon": "13d"
                }
            ],
            "speed": 16.46,
            "deg": 356,
            "gust": 18.9,
            "clouds": 100,
            "pop": 0.99,
            "rain": 1.96,
            "snow": 0.16
        },
        {
            "dt": 1618761600,
            "sunrise": 1618739875,
            "sunset": 1618788520,
            "temp": {
                "day": 46.63,
                "min": 38.28,
                "max": 49.62,
                "night": 45.75,
                "eve": 49.42,
                "morn": 38.28
            },
            "feels_like": {
                "day": 43.88,
                "night": 34.3,
                "eve": 47.08,
                "morn": 34.3
            },
            "pressure": 1010,
            "humidity": 57,
            "weather": [
                {
                    "id": 804,
                    "main": "Clouds",
                    "description": "overcast clouds",
                    "icon": "04d"
                }
            ],
            "speed": 6.08,
            "deg": 315,
            "gust": 7.02,
            "clouds": 96,
            "pop": 0
        },
        {
            "dt": 1618848000,
            "sunrise": 1618826182,
            "sunset": 1618874988,
            "temp": {
                "day": 54.41,
                "min": 42.31,
                "max": 57.4,
                "night": 49.21,
                "eve": 56.05,
                "morn": 42.31
            },
            "feels_like": {
                "day": 51.8,
                "night": 40.35,
                "eve": 53.71,
                "morn": 40.35
            },
            "pressure": 1012,
            "humidity": 48,
            "weather": [
                {
                    "id": 500,
                    "main": "Rain",
                    "description": "light rain",
                    "icon": "10d"
                }
            ],
            "speed": 4.88,
            "deg": 241,
            "gust": 9.4,
            "clouds": 85,
            "pop": 0.42,
            "rain": 0.26
        },
        {
            "dt": 1618934400,
            "sunrise": 1618912489,
            "sunset": 1618961456,
            "temp": {
                "day": 60.3,
                "min": 44.44,
                "max": 66.11,
                "night": 52.97,
                "eve": 66.11,
                "morn": 44.44
            },
            "feels_like": {
                "day": 57.87,
                "night": 42.01,
                "eve": 64.02,
                "morn": 42.01
            },
            "pressure": 1017,
            "humidity": 39,
            "weather": [
                {
                    "id": 800,
                    "main": "Clear",
                    "description": "sky is clear",
                    "icon": "01d"
                }
            ],
            "speed": 10.22,
            "deg": 205,
            "gust": 26.49,
            "clouds": 8,
            "pop": 0
        },
        {
            "dt": 1619020800,
            "sunrise": 1618998798,
            "sunset": 1619047924,
            "temp": {
                "day": 61.03,
                "min": 41.56,
                "max": 62.62,
                "night": 41.56,
                "eve": 54.1,
                "morn": 50.63
            },
            "feels_like": {
                "day": 59.56,
                "night": 48.72,
                "eve": 53.31,
                "morn": 48.72
            },
            "pressure": 1011,
            "humidity": 58,
            "weather": [
                {
                    "id": 500,
                    "main": "Rain",
                    "description": "light rain",
                    "icon": "10d"
                }
            ],
            "speed": 14.54,
            "deg": 198,
            "gust": 27.78,
            "clouds": 100,
            "pop": 1,
            "rain": 5.27
        },
        {
            "dt": 1619107200,
            "sunrise": 1619085107,
            "sunset": 1619134392,
            "temp": {
                "day": 45.79,
                "min": 35.89,
                "max": 49.86,
                "night": 41.5,
                "eve": 49.3,
                "morn": 35.89
            },
            "feels_like": {
                "day": 39.94,
                "night": 27.86,
                "eve": 44.2,
                "morn": 27.86
            },
            "pressure": 1012,
            "humidity": 31,
            "weather": [
                {
                    "id": 800,
                    "main": "Clear",
                    "description": "sky is clear",
                    "icon": "01d"
                }
            ],
            "speed": 14.5,
            "deg": 276,
            "gust": 25.03,
            "clouds": 10,
            "pop": 0.24
        },
        {
            "dt": 1619193600,
            "sunrise": 1619171418,
            "sunset": 1619220860,
            "temp": {
                "day": 51.4,
                "min": 38.43,
                "max": 57.78,
                "night": 49.03,
                "eve": 57.78,
                "morn": 38.43
            },
            "feels_like": {
                "day": 47.89,
                "night": 31.64,
                "eve": 54.66,
                "morn": 31.64
            },
            "pressure": 1018,
            "humidity": 35,
            "weather": [
                {
                    "id": 800,
                    "main": "Clear",
                    "description": "sky is clear",
                    "icon": "01d"
                }
            ],
            "speed": 14.9,
            "deg": 276,
            "gust": 24.67,
            "clouds": 6,
            "pop": 0
        },
        {
            "dt": 1619280000,
            "sunrise": 1619257729,
            "sunset": 1619307328,
            "temp": {
                "day": 50.22,
                "min": 46.98,
                "max": 54.36,
                "night": 53.35,
                "eve": 54.36,
                "morn": 46.98
            },
            "feels_like": {
                "day": 49.17,
                "night": 43.12,
                "eve": 53.53,
                "morn": 43.12
            },
            "pressure": 1015,
            "humidity": 90,
            "weather": [
                {
                    "id": 500,
                    "main": "Rain",
                    "description": "light rain",
                    "icon": "10d"
                }
            ],
            "speed": 14.27,
            "deg": 199,
            "gust": 26.11,
            "clouds": 100,
            "pop": 1,
            "rain": 2.36
        },
        {
            "dt": 1619366400,
            "sunrise": 1619344042,
            "sunset": 1619393796,
            "temp": {
                "day": 59.45,
                "min": 47.43,
                "max": 62.15,
                "night": 47.43,
                "eve": 58.71,
                "morn": 53.4
            },
            "feels_like": {
                "day": 57.63,
                "night": 53.04,
                "eve": 56.12,
                "morn": 53.04
            },
            "pressure": 1007,
            "humidity": 54,
            "weather": [
                {
                    "id": 501,
                    "main": "Rain",
                    "description": "moderate rain",
                    "icon": "10d"
                }
            ],
            "speed": 16.75,
            "deg": 315,
            "gust": 30.06,
            "clouds": 91,
            "pop": 1,
            "rain": 8.4
        },
        {
            "dt": 1619452800,
            "sunrise": 1619430355,
            "sunset": 1619480264,
            "temp": {
                "day": 56.01,
                "min": 42.49,
                "max": 62.28,
                "night": 52.95,
                "eve": 62.28,
                "morn": 42.49
            },
            "feels_like": {
                "day": 52.95,
                "night": 36.7,
                "eve": 59.9,
                "morn": 36.7
            },
            "pressure": 1025,
            "humidity": 35,
            "weather": [
                {
                    "id": 800,
                    "main": "Clear",
                    "description": "sky is clear",
                    "icon": "01d"
                }
            ],
            "speed": 11.7,
            "deg": 285,
            "gust": 27.92,
            "clouds": 6,
            "pop": 0
        },
        {
            "dt": 1619539200,
            "sunrise": 1619516670,
            "sunset": 1619566732,
            "temp": {
                "day": 66.2,
                "min": 51.69,
                "max": 77.47,
                "night": 62.22,
                "eve": 77.47,
                "morn": 52.56
            },
            "feels_like": {
                "day": 64.58,
                "night": 50.38,
                "eve": 76.6,
                "morn": 50.38
            },
            "pressure": 1019,
            "humidity": 44,
            "weather": [
                {
                    "id": 804,
                    "main": "Clouds",
                    "description": "overcast clouds",
                    "icon": "04d"
                }
            ],
            "speed": 11.72,
            "deg": 227,
            "gust": 31.27,
            "clouds": 99,
            "pop": 0
        },
        {
            "dt": 1619625600,
            "sunrise": 1619602986,
            "sunset": 1619653200,
            "temp": {
                "day": 72.81,
                "min": 60.89,
                "max": 78.71,
                "night": 63.23,
                "eve": 76.71,
                "morn": 60.89
            },
            "feels_like": {
                "day": 72.14,
                "night": 60.12,
                "eve": 76.53,
                "morn": 60.12
            },
            "pressure": 1012,
            "humidity": 50,
            "weather": [
                {
                    "id": 500,
                    "main": "Rain",
                    "description": "light rain",
                    "icon": "10d"
                }
            ],
            "speed": 13.71,
            "deg": 293,
            "gust": 27.4,
            "clouds": 100,
            "pop": 0.68,
            "rain": 1.03
        },
        {
            "dt": 1619712000,
            "sunrise": 1619689303,
            "sunset": 1619739668,
            "temp": {
                "day": 50.95,
                "min": 44.11,
                "max": 57.04,
                "night": 50.04,
                "eve": 55.22,
                "morn": 45.36
            },
            "feels_like": {
                "day": 47.01,
                "night": 38.46,
                "eve": 51.76,
                "morn": 38.46
            },
            "pressure": 1023,
            "humidity": 27,
            "weather": [
                {
                    "id": 802,
                    "main": "Clouds",
                    "description": "scattered clouds",
                    "icon": "03d"
                }
            ],
            "speed": 16.55,
            "deg": 329,
            "gust": 21.43,
            "clouds": 42,
            "pop": 0.03
        },
        {
            "dt": 1619798400,
            "sunrise": 1619775621,
            "sunset": 1619826136,
            "temp": {
                "day": 40.12,
                "min": 34.97,
                "max": 46.96,
                "night": 37.06,
                "eve": 34.97,
                "morn": 44.73
            },
            "feels_like": {
                "day": 34.05,
                "night": 40.48,
                "eve": 28.27,
                "morn": 40.48
            },
            "pressure": 1027,
            "humidity": 84,
            "weather": [
                {
                    "id": 616,
                    "main": "Snow",
                    "description": "rain and snow",
                    "icon": "13d"
                }
            ],
            "speed": 10.11,
            "deg": 47,
            "gust": 20.2,
            "clouds": 100,
            "pop": 1,
            "rain": 14.42,
            "snow": 11.62
        },
        {
            "dt": 1619884800,
            "sunrise": 1619861940,
            "sunset": 1619912604,
            "temp": {
                "day": 44.92,
                "min": 36.12,
                "max": 52.18,
                "night": 52.18,
                "eve": 52.18,
                "morn": 36.12
            },
            "feels_like": {
                "day": 41.41,
                "night": 29.01,
                "eve": 49.3,
                "morn": 29.01
            },
            "pressure": 1024,
            "humidity": 60,
            "weather": [
                {
                    "id": 500,
                    "main": "Rain",
                    "description": "light rain",
                    "icon": "10d"
                }
            ],
            "speed": 9.64,
            "deg": 354,
            "gust": 12.62,
            "clouds": 29,
            "pop": 1,
            "rain": 0.44
        }
    ]
}